{"_id":{"$oid":"5e2b173943bb0d9502e08c77"},"name":"Gurmanska","image":"https://www.restoranrecept.rs/uploads/uploaded_pictures/_content_meni/400x300/gurmanska-pljeskavica-220g-2203-838808.jpg","opis":"Gurmanska pljeskavica 380G","ocena":"4.7","cena":"460"}
{"_id":{"$oid":"5e2b173943bb0d9502e08c7a"},"name":"Kroasan sa susamom","image":"https://pekara-brankovic.com/wp-content/uploads/2015/09/Kroasan-sa-susamom-aranzman-1.jpg","opis":"Kroasan sa susamom 60g","ocena":"4.4","cena":"45"}
{"_id":{"$oid":"5e2b173943bb0d9502e08c7d"},"name":"Snikers krofna","image":"https://pekara-brankovic.com/wp-content/uploads/2019/04/Sniker-krofna.jpg","opis":"Snikers krofna 85g","ocena":"3.9","cena":"65"}
{"_id":{"$oid":"5e2b57f97cbcd186058931f2"},"name":"Majstorska pogaca","image":"https://pekara-brankovic.com/wp-content/uploads/2017/04/Pogaca-u-aranzmanu-600x391.jpg","opis":"Majstorska pogaca 450g","ocena":"3.9","cena":"55"}
{"_id":{"$oid":"5e33fc24e9c7d6eb2c4a275b"},"name":"Burek sa mesom","image":"https://pekara-brankovic.com/wp-content/uploads/2019/05/Burek-sa-mesom-aranzman.jpg","opis":"Burek sa mesom 1100g","ocena":"4.7","cena":"480"}
{"_id":{"$oid":"5e33fc24e9c7d6eb2c4a275e"},"name":"Pica klasik","image":"https://pekara-brankovic.com/wp-content/uploads/2018/10/Klasik-pica-.jpg","opis":"Pica klasik 220g","ocena":"4.8","cena":"110"}
{"_id":{"$oid":"5e33fc24e9c7d6eb2c4a2761"},"name":"Burger piletina","image":"https://pekara-brankovic.com/wp-content/uploads/2019/09/1-Burger-piletina-Sajt-2.jpg","opis":"Burger piletina 175g","ocena":"5.0","cena":"160"}
{"_id":{"$oid":"5e33fe2fe9c7d6eb2c4a2821"},"name":"Bavarski sendvic","image":"https://pekara-brankovic.com/wp-content/uploads/2016/04/bavarski-sendvic-sa-suvim-vratom-.jpg","opis":"Bavarski sendvic sa suvim vratom 170g","ocena":"3.9","cena":"120"}
{"_id":{"$oid":"5e33fe2fe9c7d6eb2c4a2824"},"name":"Madjarica","image":"https://pekara-brankovic.com/wp-content/uploads/2015/09/Madjarica-.jpg","opis":"Madjarica 100g","ocena":"4.7","cena":"90"}
{"_id":{"$oid":"5e33fe2fe9c7d6eb2c4a2827"},"name":"Coko krofnica","image":"https://pekara-brankovic.com/wp-content/uploads/2015/09/Krofnica-sa-cokoladnim-prelivom-1-1.jpg","opis":"Krofnica sa prelivom od cokolade 65g","ocena":"5.0","cena":"39"}
{"_id":{"$oid":"5e33ff28e9c7d6eb2c4a2899"},"name":"Kakao krofna","image":"https://pekara-brankovic.com/wp-content/uploads/2015/09/Krofna-sa-cokoladnim-kremom-aranzman-sajt-1.jpg","opis":"Krofnica sa kakao kremom 80g","ocena":"4.4","cena":"65"}
{"_id":{"$oid":"5e33ff28e9c7d6eb2c4a289c"},"name":"Coko kroasan","image":"https://pekara-brankovic.com/wp-content/uploads/2015/09/Preliveni-kroasan-aranzman-sajt-1.jpg","opis":"Kroasan preliven cokoladom 90g","ocena":"4.8","cena":"60"}
